myfuncbank_alex/__init__.py
myfuncbank_alex/my_func_bank.py
myfuncbank_alex/my_tkinter_draw_func_bank.py
myfuncbank_alex/my_tkinter_draw_func_bank_v2.py
myfuncbank_alex/my_tkinter_draw_func_bank_v3.py
myfuncbank_alex/my_tkinter_draw_func_bank_v3_copy.py
myfuncbank_alex/my_tkinter_draw_func_bank_v4.py
myfuncbank_alex/my_tkinter_draw_func_bank_v5.py
myfuncbank_alex/my_tkinter_draw_func_bank_v6.py
myfuncbank_alex/test.py
myfuncbank_alex-1.5.10.dist-info/METADATA
myfuncbank_alex-1.5.10.dist-info/WHEEL
myfuncbank_alex-1.5.10.dist-info/licenses/LICENSE
myfuncbank_alex-1.5.10.dist-info/RECORD
